sensirion_slf3s/__init__.py
sensirion_slf3s/base_classes.py
sensirion_slf3s/sensirion_slf3s.py
sensirion_slf3s-1.0.0.dist-info/LICENSE
sensirion_slf3s-1.0.0.dist-info/METADATA
sensirion_slf3s-1.0.0.dist-info/WHEEL
sensirion_slf3s-1.0.0.dist-info/top_level.txt
sensirion_slf3s-1.0.0.dist-info/RECORD
