Metadata-Version: 2.1
Name: sensirion_slf3s
Version: 1.0.0
Summary: Python driver for Sensirion SLF3S_XXXXX type flow sensors attached to a Sensirion SCC1-USB sensor cable. 
Author-email: "Tobias E. Naegele" <github@tobiasnaegele.com>
License: Apache License
Project-URL: Homepage, https://github.com/tnaegele/sensirion_slf3s
Project-URL: Issues, https://github.com/tnaegele/sensirion_slf3s/issues
Classifier: Programming Language :: Python :: 3
Classifier: License :: OSI Approved :: Apache Software License
Classifier: Operating System :: OS Independent
Requires-Python: >=3.8
License-File: LICENSE
Requires-Dist: numpy ==1.26.4
Requires-Dist: pyserial ==3.5
Requires-Dist: sensirion-shdlc-driver ==0.1.5
